bom_logger-1.0.5-py3.8-nspkg.pth
bom/logger/__init__.py
bom/logger/bom.conf.json
bom/logger/formatter.py
bom/logger/py.typed
bom_logger-1.0.5.dist-info/METADATA
bom_logger-1.0.5.dist-info/WHEEL
bom_logger-1.0.5.dist-info/namespace_packages.txt
bom_logger-1.0.5.dist-info/top_level.txt
bom_logger-1.0.5.dist-info/RECORD
