Metadata-Version: 2.1
Name: bom-logger
Version: 1.0.5
Summary: Log fun.
Home-page: https://github.com/bomt1me/bomlog
License: UNKNOWN
Platform: UNKNOWN
Requires-Python: >=3.8
Requires-Dist: bom-configuration
